{"remote":"23.235.39.23","identity":null,"user":null,"date":"2014-09-26T20:08:32.000Z","method":"GET","url":"http://truelovepet.disqus.com/count-data.js?2=http%3A%2F%2Fwww.truelovepetdevoto.com.ar%2Fblog%2Ffiles%2F27f1409448b3ee4573871ffa378a5c42-5.html&2=http%3A%2F%2Fwww.truelovepetdevoto.com.ar%2Fblog%2Ffiles%2Fbusco-novia.html&2=http%3A%2F%2Fwww.truelovepetdevoto.com.ar%2Fblog%2Ffiles%2Fdudas-veterinarias.html&2=http%3A%2F%2Fwww.truelovepetdevoto.com.ar%2Fblog%2Ffiles%2Fhistorias.html&2=http%3A%2F%2Fwww.truelovepetdevoto.com.ar%2Fblog%2Ffiles%2Fperdidos.html","protocol":"HTTP/1.1","status":200,"bytes":313,"referer":"http://www.truelovepetdevoto.com.ar/blog/index.html","user-agent":"Mozilla/5.0 (Windows NT 5.1) AppleWebKit/537.36 (KHTML, like Gecko) Chrome/37.0.2062.120 Safari/537.36"}